django_sb_admin-0.3.7.dist-info/DESCRIPTION.rst
django_sb_admin-0.3.7.dist-info/pbr.json
django_sb_admin-0.3.7.dist-info/WHEEL
django_sb_admin-0.3.7.dist-info/metadata.json
django_sb_admin-0.3.7.dist-info/RECORD
django_sb_admin-0.3.7.dist-info/top_level.txt
django_sb_admin-0.3.7.dist-info/METADATA
django_sb_admin/tests.py
django_sb_admin/models.py
django_sb_admin/admin.py
django_sb_admin/__init__.py
django_sb_admin/views.py
django_sb_admin/urls.py
django_sb_admin/static/fonts/glyphicons-halflings-regular.svg
django_sb_admin/static/fonts/glyphicons-halflings-regular.woff
django_sb_admin/static/fonts/glyphicons-halflings-regular.eot
django_sb_admin/static/fonts/glyphicons-halflings-regular.woff2
django_sb_admin/static/fonts/glyphicons-halflings-regular.ttf
django_sb_admin/static/font-awesome/scss/_path.scss
django_sb_admin/static/font-awesome/scss/_mixins.scss
django_sb_admin/static/font-awesome/scss/_rotated-flipped.scss
django_sb_admin/static/font-awesome/scss/_list.scss
django_sb_admin/static/font-awesome/scss/_core.scss
django_sb_admin/static/font-awesome/scss/_spinning.scss
django_sb_admin/static/font-awesome/scss/font-awesome.scss
django_sb_admin/static/font-awesome/scss/_stacked.scss
django_sb_admin/static/font-awesome/scss/_fixed-width.scss
django_sb_admin/static/font-awesome/scss/_variables.scss
django_sb_admin/static/font-awesome/scss/_larger.scss
django_sb_admin/static/font-awesome/scss/_bordered-pulled.scss
django_sb_admin/static/font-awesome/scss/_icons.scss
django_sb_admin/static/font-awesome/fonts/fontawesome-webfont.woff
django_sb_admin/static/font-awesome/fonts/FontAwesome.otf
django_sb_admin/static/font-awesome/fonts/fontawesome-webfont.ttf
django_sb_admin/static/font-awesome/fonts/fontawesome-webfont.svg
django_sb_admin/static/font-awesome/fonts/fontawesome-webfont.eot
django_sb_admin/static/font-awesome/less/icons.less
django_sb_admin/static/font-awesome/less/path.less
django_sb_admin/static/font-awesome/less/mixins.less
django_sb_admin/static/font-awesome/less/spinning.less
django_sb_admin/static/font-awesome/less/core.less
django_sb_admin/static/font-awesome/less/variables.less
django_sb_admin/static/font-awesome/less/font-awesome.less
django_sb_admin/static/font-awesome/less/larger.less
