Metadata-Version: 1.1
Name: django-sb-admin
Version: 0.3.7
Summary: SB Admin dashboard bootstrap 3 theme packaged as a reusable Django app.
Home-page: https://github.com/bluszcz/django-sb-admin
Author: Rafal Zawadzki
Author-email: bluszcz@bluszcz.net
License: Apache License version 2.0
Platform: UNKNOWN
Classifier: Environment :: Web Environment
Classifier: Framework :: Django
Classifier: Intended Audience :: Developers
Classifier: License :: OSI Approved :: Apache Software License
Classifier: Operating System :: OS Independent
Classifier: Programming Language :: Python
Classifier: Programming Language :: Python :: 3
Classifier: Programming Language :: Python :: 3.2
Classifier: Programming Language :: Python :: 3.3
Classifier: Programming Language :: Python :: 3.4
Classifier: Programming Language :: Python :: 3.5
Classifier: Programming Language :: Python :: 2.7
Classifier: Topic :: Internet :: WWW/HTTP
Classifier: Topic :: Internet :: WWW/HTTP :: Dynamic Content
